{
    "time": {
        "cpu_time_user": "00:00:03.609",
        "cpu_time_system": "00:00:00.700",
        "runtime": "00:00:04.335",
        "cpu_time_iowait": "00:00:00.000"
    },
    "peak_resources": {
        "cpu_percent": 109.4,
        "memory_rss": "590MiB",
        "memory_vms": "890MiB",
        "threads": 2
    },
    "avg_resources": {
        "cpu_percent": 95.00666666666669,
        "memory_rss": "374MiB",
        "memory_vms": "604MiB",
        "threads": 1.8666666666666667
    }
}