{
    "time": {
        "cpu_time_user": "00:01:09.819",
        "cpu_time_system": "00:00:01.620",
        "runtime": "00:00:28.683",
        "cpu_time_iowait": "00:00:00.000"
    },
    "peak_resources": {
        "cpu_percent": 410.5,
        "memory_rss": "575MiB",
        "memory_vms": "916MiB",
        "threads": 9
    },
    "avg_resources": {
        "cpu_percent": 246.729122807018,
        "memory_rss": "320MiB",
        "memory_vms": "673MiB",
        "threads": 8.628070175438591
    }
}